szurubooru_toolkit/__init__.py
szurubooru_toolkit/config.py
szurubooru_toolkit/danbooru.py
szurubooru_toolkit/deepbooru.py
szurubooru_toolkit/pixiv.py
szurubooru_toolkit/sankaku.py
szurubooru_toolkit/saucenao.py
szurubooru_toolkit/szurubooru.py
szurubooru_toolkit/utils.py
szurubooru_toolkit/scripts/__init__.py
szurubooru_toolkit/scripts/auto_tagger.py
szurubooru_toolkit/scripts/create_relations.py
szurubooru_toolkit/scripts/create_tags.py
szurubooru_toolkit/scripts/delete_posts.py
szurubooru_toolkit/scripts/import_from_booru.py
szurubooru_toolkit/scripts/import_from_url.py
szurubooru_toolkit/scripts/reset_posts.py
szurubooru_toolkit/scripts/szuru_toolkit.py
szurubooru_toolkit/scripts/tag_posts.py
szurubooru_toolkit/scripts/upload_media.py
szurubooru_toolkit-1.1.0.dist-info/licenses/LICENSE
szurubooru_toolkit-1.1.0.dist-info/METADATA
szurubooru_toolkit-1.1.0.dist-info/WHEEL
szurubooru_toolkit-1.1.0.dist-info/entry_points.txt
szurubooru_toolkit-1.1.0.dist-info/top_level.txt
szurubooru_toolkit-1.1.0.dist-info/RECORD
