Metadata-Version: 2.4
Name: szurubooru-toolkit
Version: 1.1.0
Summary: Python package and script collection to manage szurubooru.
Author-email: reluce <reluce@fkosquad.moe>
License-Expression: GPL-3.0-only
Project-URL: repository, https://github.com/reluce/szurubooru-toolkit
Project-URL: documentation, https://github.com/reluce/szurubooru-toolkit
Keywords: szurubooru,szuru,booru,saucenao,deepbooru
Requires-Python: <3.12,>=3.11
License-File: LICENSE
Requires-Dist: Pillow<10.0.0,>=9.5.0
Requires-Dist: Pybooru<5.0.0,>=4.2.2
Requires-Dist: pysaucenao<2.0.0,>=1.6.1
Requires-Dist: requests<3.0.0,>=2.25.1
Requires-Dist: tqdm<5.0.0,>=4.65.0
Requires-Dist: numpy<2.0.0,>=1.23.5
Requires-Dist: pyszuru<1.0.0,>=0.3.1
Requires-Dist: loguru<1.0.0,>=0.7.0
Requires-Dist: validators<1.0.0,>=0.20.0
Requires-Dist: gallery-dl<2.0.0,>=1.26.5
Requires-Dist: cunnypy<3.0.0,>=2.0.0
Requires-Dist: tldextract<4.0.0,>=3.4.4
Requires-Dist: flask<4.0.0,>=3.0.0
Requires-Dist: pixivpy3<4.0.0,>=3.7.4
Requires-Dist: tensorflow~=2.15.0
Dynamic: license-file
